open_notebook_mcp/__init__.py
open_notebook_mcp/server.py
open_notebook_mcp-0.3.0.dist-info/WHEEL
open_notebook_mcp-0.3.0.dist-info/entry_points.txt
open_notebook_mcp-0.3.0.dist-info/METADATA
open_notebook_mcp-0.3.0.dist-info/RECORD
