Metadata-Version: 2.3
Name: open-notebook-mcp
Version: 0.3.0
Summary: MCP server that wraps the Open Notebook API
Author: Piotr Mrzygłowski
Author-email: Piotr Mrzygłowski <piotr@epochal.dev>
Requires-Dist: httpx>=0.28.1
Requires-Dist: mcp[cli]>=1.23.2
Requires-Python: >=3.12
Project-URL: Homepage, https://github.com/Epochal-dev/open-notebook-mcp
Project-URL: Repository, https://github.com/Epochal-dev/open-notebook-mcp
